blobtoolkit_pipeline.py
blobtoolkit-snakefiles/add_reads.smk
blobtoolkit-snakefiles/blastn.smk
blobtoolkit-snakefiles/blobtoolkit.smk
blobtoolkit-snakefiles/blobtools.smk
blobtoolkit-snakefiles/busco.smk
blobtoolkit-snakefiles/chunk_stats.smk
blobtoolkit-snakefiles/cov_stats.smk
blobtoolkit-snakefiles/diamond.smk
blobtoolkit-snakefiles/diamond_blastp.smk
blobtoolkit-snakefiles/minimap.smk
blobtoolkit-snakefiles/view.smk
blobtoolkit-snakefiles/window_stats.smk
blobtoolkit-snakefiles/windowmasker.smk
blobtoolkit-snakefiles/rules/_transfer_dataset.smk
blobtoolkit-snakefiles/rules/add_cov_to_tsv.smk
blobtoolkit-snakefiles/rules/add_summary_to_metadata.smk
blobtoolkit-snakefiles/rules/checksum_files.smk
blobtoolkit-snakefiles/rules/chunk_fasta.smk
blobtoolkit-snakefiles/rules/chunk_fasta_by_busco.smk
blobtoolkit-snakefiles/rules/chunk_nohit_fasta.smk
blobtoolkit-snakefiles/rules/combine_stats.smk
blobtoolkit-snakefiles/rules/count_busco_genes.smk
blobtoolkit-snakefiles/rules/extract_busco_genes.smk
blobtoolkit-snakefiles/rules/extract_nohit_fasta.smk
blobtoolkit-snakefiles/rules/generate_images.smk
blobtoolkit-snakefiles/rules/generate_summary.smk
blobtoolkit-snakefiles/rules/get_chunked_stats.smk
blobtoolkit-snakefiles/rules/get_window_stats.smk
blobtoolkit-snakefiles/rules/run_bamtools_stats.smk
blobtoolkit-snakefiles/rules/run_blastn.smk
blobtoolkit-snakefiles/rules/run_blobtk_depth.smk
blobtoolkit-snakefiles/rules/run_blobtools_add.smk
blobtoolkit-snakefiles/rules/run_blobtools_create.smk
blobtoolkit-snakefiles/rules/run_busco5.smk
blobtoolkit-snakefiles/rules/run_diamond_blastp.smk
blobtoolkit-snakefiles/rules/run_diamond_blastx.smk
blobtoolkit-snakefiles/rules/run_minimap2_align.smk
blobtoolkit-snakefiles/rules/run_minimap2_index.smk
blobtoolkit-snakefiles/rules/run_mosdepth.smk
blobtoolkit-snakefiles/rules/run_sub_pipeline.smk
blobtoolkit-snakefiles/rules/run_windowmasker.smk
blobtoolkit-snakefiles/rules/skip_windowmasker.smk
blobtoolkit_pipeline-4.5.0.dist-info/METADATA
blobtoolkit_pipeline-4.5.0.dist-info/WHEEL
blobtoolkit_pipeline-4.5.0.dist-info/entry_points.txt
blobtoolkit_pipeline-4.5.0.dist-info/top_level.txt
blobtoolkit_pipeline-4.5.0.dist-info/RECORD
