Metadata-Version: 2.1
Name: blobtoolkit-pipeline
Version: 4.5.0
Summary: blobtoolkit-pipeline
Home-page: https://github.com/blobtoolkit/blobtoolkit
Author: blobtoolkit
Author-email: blobtoolkit@genomehubs.org
License: UNKNOWN
Project-URL: Bug Reports, https://github.com/blobtoolkit/blobtoolkit/issues
Project-URL: Source, https://github.com/blobtoolkit/blobtoolkit
Keywords: bioinformatics
Platform: UNKNOWN
Classifier: Development Status :: 5 - Production/Stable
Classifier: Intended Audience :: Science/Research
Classifier: Topic :: Scientific/Engineering :: Bio-Informatics
Classifier: License :: OSI Approved :: MIT License
Classifier: Programming Language :: Python :: 3
Classifier: Programming Language :: Python :: 3.6
Classifier: Programming Language :: Python :: 3.7
Classifier: Programming Language :: Python :: 3.8
Classifier: Programming Language :: Python :: 3.9
Classifier: Programming Language :: Python :: 3.10
Classifier: Programming Language :: Python :: 3.11
Classifier: Programming Language :: Python :: 3 :: Only
Requires-Python: >=3.9, <3.14
Requires-Dist: docopt>=0.6.2
Requires-Dist: psutil==5.9.4
Requires-Dist: pyyaml
Requires-Dist: tolkein>=0.5.0
Requires-Dist: tqdm==4.64.1
Requires-Dist: ujson>=5.7.0
Requires-Dist: defusedxml==0.7.1
Requires-Dist: requests>=2.28.1
Requires-Dist: snakemake==7.19.1
Requires-Dist: pulp==2.7.0
Provides-Extra: dev
Requires-Dist: pycodestyle>=2.6.0; extra == "dev"
Requires-Dist: pydocstyle>=5.0.2; extra == "dev"
Requires-Dist: pylint>=2.5.3; extra == "dev"
Provides-Extra: test
Requires-Dist: coverage>=5.1; extra == "test"
Requires-Dist: coveralls>=2.0.0; extra == "test"
Requires-Dist: mock>=4.0.2; extra == "test"
Requires-Dist: pytest-cov>=2.10.0; extra == "test"
Requires-Dist: pytest-isort>=5; extra == "test"
Requires-Dist: pytest-mock>=3.1.1; extra == "test"
Requires-Dist: pytest>=6.0.0; extra == "test"
